{
    "displayName": "Level N Cat5600",
    "id": "LNC000001",
    "parentCat": {
        "displayName": "Level Three Cat5543",
        "id": "LTC000004",
        "version": 1
    },
    "productList": [
        {
            "description": "The brand a great that has Roadester, Model S and Model X, Model 3 is in development5637",
            "displayName": "Jeans5635",
            "id": "P000006",
            "origin": "China",
            "version": 1
        },
        {
            "description": "The brand a great that has Roadester, Model S and Model X, Model 3 is in development5643",
            "displayName": "Jeans5641",
            "id": "P000008",
            "origin": "Japan",
            "version": 1
        },
        {
            "description": "The brand a great that has Roadester, Model S and Model X, Model 3 is in development5652",
            "displayName": "Jeans5650",
            "id": "P000011",
            "origin": "French",
            "version": 1
        },
        {
            "description": "The brand a great that has Roadester, Model S and Model X, Model 3 is in development5661",
            "displayName": "Jeans5659",
            "id": "P000014",
            "origin": "China",
            "version": 1
        },
        {
            "description": "The brand a great that has Roadester, Model S and Model X, Model 3 is in development5664",
            "displayName": "Jeans5662",
            "id": "P000015",
            "origin": "French",
            "version": 1
        }
    ],
    "version": 1
}
